django_squash/__init__.py
django_squash/apps.py
django_squash/settings.py
django_squash/contrib/__init__.py
django_squash/contrib/postgres.py
django_squash/db/__init__.py
django_squash/db/migrations/__init__.py
django_squash/db/migrations/autodetector.py
django_squash/db/migrations/loader.py
django_squash/db/migrations/operators.py
django_squash/db/migrations/questioner.py
django_squash/db/migrations/serializer.py
django_squash/db/migrations/utils.py
django_squash/db/migrations/writer.py
django_squash/management/__init__.py
django_squash/management/commands/__init__.py
django_squash/management/commands/squash_migrations.py
django_squash-0.0.15.dist-info/licenses/LICENSE
django_squash-0.0.15.dist-info/METADATA
django_squash-0.0.15.dist-info/WHEEL
django_squash-0.0.15.dist-info/top_level.txt
django_squash-0.0.15.dist-info/zip-safe
django_squash-0.0.15.dist-info/RECORD
