Metadata-Version: 2.4
Name: django_squash
Version: 0.0.15
Summary: A migration squasher that doesn't care how Humpty Dumpty was put together.
Author-email: Javier Buzzi <buzzi.javier@gmail.com>
License-Expression: MIT
Project-URL: homepage, https://github.com/kingbuzzman/django-squash
Keywords: django,migration,squashing,squash
Platform: any
Classifier: Development Status :: 5 - Production/Stable
Classifier: Environment :: Console
Classifier: Intended Audience :: Developers
Classifier: Framework :: Django
Classifier: Framework :: Django :: 4.2
Classifier: Framework :: Django :: 5.1
Classifier: Framework :: Django :: 5.2
Classifier: Programming Language :: Python
Classifier: Programming Language :: Python :: 3
Classifier: Programming Language :: Python :: 3.9
Classifier: Programming Language :: Python :: 3.10
Classifier: Programming Language :: Python :: 3.11
Classifier: Programming Language :: Python :: 3.12
Classifier: Programming Language :: Python :: 3.13
Classifier: Programming Language :: Python :: Implementation :: CPython
Classifier: Programming Language :: Python :: Implementation :: PyPy
Classifier: Topic :: Software Development :: Libraries :: Python Modules
Classifier: Topic :: Utilities
Requires-Python: >=3.9
License-File: LICENSE
Requires-Dist: django>=4.2
Provides-Extra: lint
Requires-Dist: pygments; extra == "lint"
Requires-Dist: restructuredtext-lint; extra == "lint"
Requires-Dist: ruff; extra == "lint"
Requires-Dist: vulture; extra == "lint"
Requires-Dist: zizmor; extra == "lint"
Provides-Extra: test
Requires-Dist: black; extra == "test"
Requires-Dist: build; extra == "test"
Requires-Dist: ipdb; extra == "test"
Requires-Dist: libcst; extra == "test"
Requires-Dist: psycopg2-binary; extra == "test"
Requires-Dist: pytest-cov; extra == "test"
Requires-Dist: pytest-django; extra == "test"
Dynamic: license-file
